{"_id":"markdown-table","_rev":"17-b326065cca597d0cd5e9329f6c2d5ffd","name":"markdown-table","description":"Markdown/ASCII tables","dist-tags":{"latest":"1.0.0"},"versions":{"0.0.1":{"name":"markdown-table","version":"0.0.1","description":"Markdown tables, with alignment","license":"MIT","keywords":["text","markdown","table","align","ascii","rows","tabular"],"repository":{"type":"git","url":"https://github.com/wooorm/markdown-table.git"},"author":{"name":"Titus Wormer","email":"tituswormer@gmail.com"},"devDependencies":{"chalk":"^0.5.1","eslint":"^0.8.0","istanbul":"^0.3.0","jscs":"^1.5.0","mocha":"^1.20.0"},"scripts":{"test":"_mocha --reporter spec --check-leaks -u exports spec/markdown-table.spec.js","test-travis":"istanbul cover node_modules/.bin/_mocha --report lcovonly -- --reporter spec --check-leaks -u exports spec/markdown-table.spec.js","lint":"npm run lint-api && npm run lint-test && npm run lint-style","lint-api":"eslint index.js --env node --env browser --rule 'quotes: [2, single]'","lint-test":"eslint spec/markdown-table.spec.js --env node --env mocha --rule 'quotes: [2, single]'","lint-style":"jscs index.js spec/markdown-table.spec.js --reporter=inline","coverage":"istanbul cover node_modules/.bin/_mocha -- -- spec/markdown-table.spec.js","make":"npm run lint && npm run coverage"},"gitHead":"34cf9623e6829cc51a8aa3eecc790019f6868a75","bugs":{"url":"https://github.com/wooorm/markdown-table/issues"},"homepage":"https://github.com/wooorm/markdown-table","_id":"markdown-table@0.0.1","_shasum":"160e159988624b28c9503e7e034025bb26ba8114","_from":".","_npmVersion":"2.0.0","_npmUser":{"name":"wooorm","email":"tituswormer@gmail.com"},"maintainers":[{"name":"wooorm","email":"tituswormer@gmail.com"}],"dist":{"shasum":"160e159988624b28c9503e7e034025bb26ba8114","tarball":"https://registry.npmjs.org/markdown-table/-/markdown-table-0.0.1.tgz"},"directories":{}},"0.1.0":{"name":"markdown-table","version":"0.1.0","description":"Markdown tables, with alignment","license":"MIT","keywords":["text","markdown","table","align","ascii","rows","tabular"],"repository":{"type":"git","url":"https://github.com/wooorm/markdown-table.git"},"author":{"name":"Titus Wormer","email":"tituswormer@gmail.com"},"devDependencies":{"chalk":"^0.5.0","eslint":"^0.9.0","istanbul":"^0.3.0","jscs":"^1.7.0","mocha":"^2.0.0"},"scripts":{"test":"_mocha --reporter spec --check-leaks -u exports test.js","test-travis":"istanbul cover node_modules/.bin/_mocha --report lcovonly -- --reporter spec --check-leaks -u exports test.js","lint":"npm run lint-api && npm run lint-test && npm run lint-style","lint-api":"eslint index.js","lint-test":"eslint test.js --env mocha","lint-style":"jscs index.js test.js --reporter=inline","coverage":"istanbul cover node_modules/.bin/_mocha -- -- test.js","make":"npm run lint && npm run coverage"},"gitHead":"7ece551da8f82c2c61f71d18586207514e10d87f","bugs":{"url":"https://github.com/wooorm/markdown-table/issues"},"homepage":"https://github.com/wooorm/markdown-table","_id":"markdown-table@0.1.0","_shasum":"c6beb1c34c2f4b5e204f20e38250c2e887ca4499","_from":".","_npmVersion":"1.4.28","_npmUser":{"name":"wooorm","email":"tituswormer@gmail.com"},"maintainers":[{"name":"wooorm","email":"tituswormer@gmail.com"}],"dist":{"shasum":"c6beb1c34c2f4b5e204f20e38250c2e887ca4499","tarball":"https://registry.npmjs.org/markdown-table/-/markdown-table-0.1.0.tgz"},"directories":{}},"0.2.0":{"name":"markdown-table","version":"0.2.0","description":"Markdown/ASCII tables","license":"MIT","keywords":["text","markdown","table","align","ascii","rows","tabular"],"repository":{"type":"git","url":"https://github.com/wooorm/markdown-table.git"},"author":{"name":"Titus Wormer","email":"tituswormer@gmail.com"},"devDependencies":{"chalk":"^0.5.0","eslint":"^0.10.0","istanbul":"^0.3.0","jscs":"^1.0.0","mocha":"^2.0.0"},"scripts":{"test":"_mocha --reporter spec --check-leaks -u exports test.js","test-travis":"istanbul cover node_modules/.bin/_mocha --report lcovonly -- --reporter spec --check-leaks -u exports test.js","coverage":"istanbul cover node_modules/.bin/_mocha -- -- test.js","lint-api":"eslint index.js","lint-test":"eslint test.js --env mocha","lint-style":"jscs index.js test.js --reporter=inline","lint":"npm run lint-api && npm run lint-test && npm run lint-style","make":"npm run lint && npm run coverage"},"gitHead":"9e57242e5f483542ffb5f722b693b90fafe5bfb9","bugs":{"url":"https://github.com/wooorm/markdown-table/issues"},"homepage":"https://github.com/wooorm/markdown-table","_id":"markdown-table@0.2.0","_shasum":"6a5855c983d07686a3068f22a7b8bf3f5110b5af","_from":".","_npmVersion":"1.4.28","_npmUser":{"name":"wooorm","email":"tituswormer@gmail.com"},"maintainers":[{"name":"wooorm","email":"tituswormer@gmail.com"}],"dist":{"shasum":"6a5855c983d07686a3068f22a7b8bf3f5110b5af","tarball":"https://registry.npmjs.org/markdown-table/-/markdown-table-0.2.0.tgz"},"directories":{}},"0.3.0":{"name":"markdown-table","version":"0.3.0","description":"Markdown/ASCII tables","license":"MIT","keywords":["text","markdown","table","align","ascii","rows","tabular"],"repository":{"type":"git","url":"https://github.com/wooorm/markdown-table.git"},"author":{"name":"Titus Wormer","email":"tituswormer@gmail.com"},"devDependencies":{"chalk":"^0.5.0","eslint":"^0.10.0","istanbul":"^0.3.0","jscs":"^1.0.0","jscs-jsdoc":"^0.3.0","mocha":"^2.0.0"},"scripts":{"test":"_mocha --check-leaks test.js","test-travis":"istanbul cover _mocha --report lcovonly -- --check-leaks test.js","coverage":"istanbul cover _mocha -- -- test.js","lint-api":"eslint index.js","lint-test":"eslint --env mocha test.js","lint-style":"jscs --reporter inline index.js test.js","lint":"npm run lint-api && npm run lint-test && npm run lint-style","make":"npm run lint && npm run coverage"},"gitHead":"c27f5a21523d1a7c1957507cd77afcb32aa0a2bb","bugs":{"url":"https://github.com/wooorm/markdown-table/issues"},"homepage":"https://github.com/wooorm/markdown-table","_id":"markdown-table@0.3.0","_shasum":"2e41334fc034a045822c173a40a9230eeab8c9bf","_from":".","_npmVersion":"2.0.0","_npmUser":{"name":"wooorm","email":"tituswormer@gmail.com"},"maintainers":[{"name":"wooorm","email":"tituswormer@gmail.com"}],"dist":{"shasum":"2e41334fc034a045822c173a40a9230eeab8c9bf","tarball":"https://registry.npmjs.org/markdown-table/-/markdown-table-0.3.0.tgz"},"directories":{}},"0.3.1":{"name":"markdown-table","version":"0.3.1","description":"Markdown/ASCII tables","license":"MIT","keywords":["text","markdown","table","align","ascii","rows","tabular"],"repository":{"type":"git","url":"https://github.com/wooorm/markdown-table.git"},"author":{"name":"Titus Wormer","email":"tituswormer@gmail.com"},"devDependencies":{"chalk":"^0.5.0","eslint":"^0.10.0","istanbul":"^0.3.0","jscs":"^1.0.0","jscs-jsdoc":"^0.3.0","mocha":"^2.0.0"},"scripts":{"test":"_mocha --check-leaks test.js","test-travis":"istanbul cover _mocha --report lcovonly -- --check-leaks test.js","coverage":"istanbul cover _mocha -- -- test.js","lint-api":"eslint index.js","lint-test":"eslint --env mocha test.js","lint-style":"jscs --reporter inline index.js test.js","lint":"npm run lint-api && npm run lint-test && npm run lint-style","make":"npm run lint && npm run coverage"},"gitHead":"e14481ce4e67b43c3970ce04288507b0693da2af","bugs":{"url":"https://github.com/wooorm/markdown-table/issues"},"homepage":"https://github.com/wooorm/markdown-table","_id":"markdown-table@0.3.1","_shasum":"3be041e26b52198c69de2c7d2afd7f91d3ce04eb","_from":".","_npmVersion":"2.0.0","_npmUser":{"name":"wooorm","email":"tituswormer@gmail.com"},"maintainers":[{"name":"wooorm","email":"tituswormer@gmail.com"}],"dist":{"shasum":"3be041e26b52198c69de2c7d2afd7f91d3ce04eb","tarball":"https://registry.npmjs.org/markdown-table/-/markdown-table-0.3.1.tgz"},"directories":{}},"0.3.2":{"name":"markdown-table","version":"0.3.2","description":"Markdown/ASCII tables","license":"MIT","keywords":["text","markdown","table","align","ascii","rows","tabular"],"repository":{"type":"git","url":"https://github.com/wooorm/markdown-table.git"},"author":{"name":"Titus Wormer","email":"tituswormer@gmail.com"},"devDependencies":{"chalk":"^0.5.0","eslint":"^0.12.0","istanbul":"^0.3.0","jscs":"^1.0.0","jscs-jsdoc":"^0.4.0","mocha":"^2.0.0"},"scripts":{"test-api":"_mocha --check-leaks test.js","test-coveralls":"istanbul cover _mocha --report lcovonly -- --check-leaks test.js","test-coverage":"istanbul cover _mocha -- -- test.js","test-travis":"npm run test-coveralls","test":"npm run test-api","lint-api":"eslint index.js","lint-test":"eslint --env mocha test.js","lint-style":"jscs --reporter inline index.js test.js","lint":"npm run lint-api && npm run lint-test && npm run lint-style","make":"npm run lint && npm run test-coverage"},"gitHead":"75b8a337eb10291d5b5e2930b3d7079e7303da3f","bugs":{"url":"https://github.com/wooorm/markdown-table/issues"},"homepage":"https://github.com/wooorm/markdown-table","_id":"markdown-table@0.3.2","_shasum":"ab0501425117218c498754d57e244dcd4a80232e","_from":".","_npmVersion":"1.4.28","_npmUser":{"name":"wooorm","email":"tituswormer@gmail.com"},"maintainers":[{"name":"wooorm","email":"tituswormer@gmail.com"}],"dist":{"shasum":"ab0501425117218c498754d57e244dcd4a80232e","tarball":"https://registry.npmjs.org/markdown-table/-/markdown-table-0.3.2.tgz"},"directories":{}},"0.4.0":{"name":"markdown-table","version":"0.4.0","description":"Markdown/ASCII tables","license":"MIT","keywords":["text","markdown","table","align","ascii","rows","tabular"],"repository":{"type":"git","url":"https://github.com/wooorm/markdown-table.git"},"author":{"name":"Titus Wormer","email":"tituswormer@gmail.com"},"devDependencies":{"chalk":"^1.0.0","eslint":"^0.18.0","istanbul":"^0.3.0","jscs":"^1.0.0","jscs-jsdoc":"^0.4.0","mocha":"^2.0.0"},"scripts":{"test-api":"_mocha --check-leaks test.js","test-coveralls":"istanbul cover _mocha --report lcovonly -- --check-leaks test.js","test-coverage":"istanbul cover _mocha -- -- test.js","test-travis":"npm run test-coveralls","test":"npm run test-api","lint-api":"eslint index.js","lint-test":"eslint --env mocha test.js","lint-style":"jscs --reporter inline index.js test.js","lint":"npm run lint-api && npm run lint-test && npm run lint-style","make":"npm run lint && npm run test-coverage"},"gitHead":"500964b100c0261c8f731bbb9c3617a624b5b255","bugs":{"url":"https://github.com/wooorm/markdown-table/issues"},"homepage":"https://github.com/wooorm/markdown-table","_id":"markdown-table@0.4.0","_shasum":"890c2c1b3bfe83fb00e4129b8e4cfe645270f9d1","_from":".","_npmVersion":"2.7.4","_nodeVersion":"1.6.3","_npmUser":{"name":"wooorm","email":"tituswormer@gmail.com"},"maintainers":[{"name":"wooorm","email":"tituswormer@gmail.com"}],"dist":{"shasum":"890c2c1b3bfe83fb00e4129b8e4cfe645270f9d1","tarball":"https://registry.npmjs.org/markdown-table/-/markdown-table-0.4.0.tgz"},"directories":{}},"1.0.0":{"name":"markdown-table","version":"1.0.0","description":"Markdown/ASCII tables","license":"MIT","keywords":["text","markdown","table","align","ascii","rows","tabular"],"dependencies":{},"repository":{"type":"git","url":"git+https://github.com/wooorm/markdown-table.git"},"bugs":{"url":"https://github.com/wooorm/markdown-table/issues"},"author":{"name":"Titus Wormer","email":"tituswormer@gmail.com","url":"http://wooorm.com"},"contributors":[{"name":"Titus Wormer","email":"tituswormer@gmail.com","url":"http://wooorm.com"}],"engines":{"node":">=0.11.0"},"files":["index.js"],"devDependencies":{"browserify":"^13.0.0","chalk":"^1.1.3","esmangle":"^1.0.0","nyc":"^7.1.0","remark-cli":"^1.0.0","remark-comment-config":"^4.0.0","remark-github":"^5.0.0","remark-lint":"^4.0.0","remark-validate-links":"^4.0.0","tape":"^4.4.0","xo":"^0.16.0"},"scripts":{"build-md":"remark . --quiet --frail","build-bundle":"browserify index.js -s markdownTable > markdown-table.js","build-mangle":"esmangle markdown-table.js > markdown-table.min.js","build":"npm run build-md && npm run build-bundle && npm run build-mangle","lint":"xo","test-api":"node test","test-coverage":"nyc --reporter lcov tape test.js","test":"npm run build && npm run lint && npm run test-coverage"},"nyc":{"check-coverage":true,"lines":100,"functions":100,"branches":100},"xo":{"space":true,"rules":{"complexity":"off"},"ignores":["markdown-table.js","markdown-table.min.js"]},"remarkConfig":{"output":true,"plugins":{"comment-config":null,"lint":{"heading-increment":false,"list-item-spacing":false},"github":null,"validate-links":null},"settings":{"bullet":"*"}},"gitHead":"028dc649673cde1ff510272d24e7602f951c6358","homepage":"https://github.com/wooorm/markdown-table#readme","_id":"markdown-table@1.0.0","_shasum":"5f768d5ae1b98f31ce673cd24686251decf2c460","_from":".","_npmVersion":"3.3.6","_nodeVersion":"5.0.0","_npmUser":{"name":"wooorm","email":"tituswormer@gmail.com"},"dist":{"shasum":"5f768d5ae1b98f31ce673cd24686251decf2c460","tarball":"https://registry.npmjs.org/markdown-table/-/markdown-table-1.0.0.tgz"},"maintainers":[{"name":"wooorm","email":"tituswormer@gmail.com"}],"_npmOperationalInternal":{"host":"packages-12-west.internal.npmjs.com","tmp":"tmp/markdown-table-1.0.0.tgz_1470847648147_0.9012498874217272"},"directories":{}}},"readme":"# markdown-table [![Build Status][travis-badge]][travis] [![Coverage Status][codecov-badge]][codecov]\n\nGenerate fancy [Markdown][fancy]/ASCII tables.\n\n## Installation\n\n[npm][]:\n\n```bash\nnpm install markdown-table\n```\n\n## Usage\n\nDependencies:\n\n```javascript\nvar table = require('markdown-table');\n```\n\nNormal usage (defaults to left-alignment):\n\n```javascript\ntable([\n  ['Branch', 'Commit'],\n  ['master', '0123456789abcdef'],\n  ['staging', 'fedcba9876543210']\n]);\n```\n\nYields:\n\n```txt\n| Branch  | Commit           |\n| ------- | ---------------- |\n| master  | 0123456789abcdef |\n| staging | fedcba9876543210 |\n```\n\nWith alignment:\n\n```javascript\ntable([\n  ['Beep', 'No.', 'Boop'],\n  ['beep', '1024', 'xyz'],\n  ['boop', '3388450', 'tuv'],\n  ['foo', '10106', 'qrstuv'],\n  ['bar', '45', 'lmno']\n], {\n  align: ['l', 'c', 'r']\n});\n```\n\nYields:\n\n```txt\n| Beep |   No.   |   Boop |\n| :--- | :-----: | -----: |\n| beep |   1024  |    xyz |\n| boop | 3388450 |    tuv |\n| foo  |  10106  | qrstuv |\n| bar  |    45   |   lmno |\n```\n\nAlignment on dots:\n\n```javascript\ntable([\n  ['No.'],\n  ['0.1.2'],\n  ['11.22.33'],\n  ['5.6.'],\n  ['1.22222'],\n], {\n  align: '.'\n});\n```\n\nYields:\n\n```txt\n|    No.      |\n| :---------: |\n|   0.1.2     |\n| 11.22.33    |\n|   5.6.      |\n|     1.22222 |\n```\n\n## API\n\n### `markdownTable(table[, options])`\n\nTurns a given matrix of strings (an array of arrays of strings) into a table.\n\n###### `options`\n\nThe following options are available:\n\n*   `options.align` (`string` or `Array.<string>`)\n    — One style for all columns, or styles for their respective\n    columns.  Each style is either `'l'` (left), `'r'` (right), `'c'`\n    (centre), or `'.'` (dot).  Other values are treated as `''`, which\n    doesn’t place the colon but does left align.  _Only the lowercased\n    first character is used, so `Right` is fine_;\n*   `options.delimiter` (`string`, default: `' | '`)\n    — Value to insert between cells. Careful, setting this to a\n    non-pipe breaks GitHub Flavoured Markdown;\n*   `options.start` (`string`, default: `'| '`)\n    — Value to insert at the beginning of every row.\n*   `options.end` (`string`, default: `' |'`)\n    — Value to insert at the end of every row.\n*   `options.rule` (`boolean`, default: `true`)\n    — Whether to display a rule between the header and the body of the\n    table.  Careful, will break GitHub Flavoured Markdown when `false`;\n*   `options.stringLength` ([`Function`][length], default:\n    `s => s.length`)\n    — Method to detect the length of a cell (see below).\n\n### `stringLength(cell)`\n\nANSI-sequences mess up tables on terminals. To fix this, you have to\npass in a `stringLength` option to detect the “visible” length of a\ncell.\n\n```javascript\nvar chalk = require('chalk');\n\nfunction stringLength(cell) {\n  return chalk.stripColor(cell).length;\n}\n```\n\n## Inspiration\n\nThe original idea and basic implementation was inspired by James\nHalliday's [text-table][] library.\n\n## License\n\n[MIT][license] © [Titus Wormer][author]\n\n<!-- Definitions -->\n\n[travis-badge]: https://img.shields.io/travis/wooorm/markdown-table.svg\n\n[travis]: https://travis-ci.org/wooorm/markdown-table\n\n[codecov-badge]: https://img.shields.io/codecov/c/github/wooorm/markdown-table.svg\n\n[codecov]: https://codecov.io/github/wooorm/markdown-table\n\n[npm]: https://docs.npmjs.com/cli/install\n\n[license]: LICENSE\n\n[author]: http://wooorm.com\n\n[fancy]: https://help.github.com/articles/github-flavored-markdown/#tables\n\n[length]: #stringlengthcell\n\n[text-table]: https://github.com/substack/text-table\n","maintainers":[{"name":"wooorm","email":"tituswormer@gmail.com"}],"time":{"modified":"2016-10-08T04:23:02.717Z","created":"2014-10-04T17:32:26.220Z","0.0.1":"2014-10-04T17:32:26.220Z","0.1.0":"2014-10-30T19:40:31.404Z","0.2.0":"2014-11-29T14:03:40.719Z","0.3.0":"2014-12-19T20:19:58.859Z","0.3.1":"2014-12-26T13:11:09.716Z","0.3.2":"2015-01-22T18:48:34.436Z","0.4.0":"2015-04-08T18:20:12.197Z","1.0.0":"2016-08-10T16:47:29.890Z"},"homepage":"https://github.com/wooorm/markdown-table#readme","keywords":["text","markdown","table","align","ascii","rows","tabular"],"repository":{"type":"git","url":"git+https://github.com/wooorm/markdown-table.git"},"author":{"name":"Titus Wormer","email":"tituswormer@gmail.com","url":"http://wooorm.com"},"bugs":{"url":"https://github.com/wooorm/markdown-table/issues"},"license":"MIT","readmeFilename":"readme.md","users":{"dotnil":true,"doodlewind":true,"ahmed-dinar":true},"contributors":[{"name":"Titus Wormer","email":"tituswormer@gmail.com","url":"http://wooorm.com"}],"_attachments":{},"_etag":"\"1TR9QTXJLSJLWVEB7GR0LK47T\""}